financialPlot/__init__.py
financialPlot/financialPlot.py
financialPlot-1.dist-info/LICENSE.txt
financialPlot-1.dist-info/METADATA
financialPlot-1.dist-info/WHEEL
financialPlot-1.dist-info/top_level.txt
financialPlot-1.dist-info/RECORD
