Metadata-Version: 2.1
Name: financialPlot
Version: 1
Summary: Visualizing tools of financial statement built on plotly.
Home-page: https://github.com/GyeongahNa
Author: Gna
Author-email: luckyrookie@khu.ac.kr
License: MIT
Platform: UNKNOWN
Classifier: Programming Language :: Python :: 3
Classifier: License :: OSI Approved :: MIT License
Classifier: Operating System :: OS Independent
